[
  {
    "state": "app.dashboard",
    "title": "Dashboard",
    "type": "link",
    "icon": "dashboard"
  },
  {
    "state": "app.forum.thread-groups",
    "title": "Forum",
    "type": "link",
    "icon": "forum"
  },
  {
    "state": "app",
    "title": "Report",
    "icon": "assessment",
    "type": "toggle",
    "pages": [
      {
        "state": "app.reports.balance-report",
        "title": "Balance",
        "type": "link",
        "icon": ""
      },
      {
        "state": "app.reports.pnl-report",
        "title": "P&L",
        "type": "link",
        "icon": ""
      },
      {
        "state": "app.reports.performance-report",
        "title": "Performance",
        "type": "link",
        "icon": ""
      },
      {
        "state": "app.reports.cash-flow-projection-report",
        "title": "Cash flow",
        "type": "link",
        "icon": ""
      },
      {
        "state": "app.reports.transaction-report",
        "title": "Transaction",
        "type": "link",
        "icon": ""
      }
    ]
  },
  {
    "state": "",
    "title": "Data",
    "icon": "view_compact",
    "type": "toggle",
    "pages": [
      {
        "state": "app.data.portfolio",
        "title": "Portfolio",
        "type": "link",
        "icon": ""
      },
      {
        "state": "app.data.account",
        "title": "Account",
        "type": "link",
        "icon": ""
      },
      {
        "state": "app.data.account-type",
        "title": "Account Type",
        "type": "link",
        "icon": ""
      },
      {
        "state": "",
        "title": "Responsible",
        "type": "toggle",
        "pages": [
          {
            "state": "app.data.responsible-group",
            "title": "Group",
            "type": "link",
            "icon": ""
          },
          {
            "state": "app.data.responsible",
            "title": "Responsible",
            "type": "link",
            "icon": ""
          }
        ]
      },
      {
        "state": "",
        "title": "Counterparty",
        "type": "toggle",
        "pages": [
          {
            "state": "app.data.counterparty-group",
            "title": "Group",
            "type": "link",
            "icon": ""
          },
          {
            "state": "app.data.counterparty",
            "title": "Counterparty",
            "type": "link",
            "icon": ""
          }
        ]
      },
      {
        "state": "app.data.instrument",
        "title": "Instrument",
        "type": "link",
        "icon": ""
      },
      {
        "state": "app.data.instrument-type",
        "title": "Instrument Type",
        "type": "link",
        "icon": ""
      },
      {
        "state": "app.data.pricing-policy",
        "title": "Pricing policy",
        "type": "link",
        "icon": ""
      },
      {
        "state": "app.data.currency",
        "title": "Currency",
        "type": "link",
        "icon": ""
      },
      {
        "state": "app.data.complex-transaction",
        "title": "Transactions",
        "type": "link",
        "icon": ""
      },
      {
        "state": "app.data.transaction",
        "title": "Base Transaction",
        "type": "link",
        "icon": ""
      },
      {
        "state": "",
        "title": "Transaction Type",
        "type": "toggle",
        "pages": [
          {
            "state": "app.data.transaction-type-group",
            "title": "Group",
            "type": "link",
            "icon": ""
          },
          {
            "state": "app.data.transaction-type",
            "title": "Type",
            "type": "link",
            "icon": ""
          }
        ]
      },
      {
        "state": "app.data.price-history",
        "title": "Price history",
        "type": "link",
        "icon": ""
      },
      {
        "state": "app.data.currency-history",
        "title": "FX history",
        "type": "link",
        "icon": ""
      },
      {
        "state": "app.data.tag",
        "title": "Tags",
        "type": "link",
        "icon": ""
      }
    ]
  },
  {
    "state": "",
    "title": "REFERENCE",
    "icon": "view_compact",
    "type": "toggle",
    "pages": [
      {
        "state": "",
        "title": "Strategy 1",
        "icon": "",
        "type": "toggle",
        "pages": [
          {
            "state": "app.data.strategy-group({strategyNumber: 1})",
            "title": "Group",
            "type": "link",
            "icon": ""
          },
          {
            "state": "app.data.strategy-subgroup({strategyNumber: 1})",
            "title": "Subgroup",
            "type": "link",
            "icon": ""
          },
          {
            "state": "app.data.strategy({strategyNumber: 1})",
            "title": "Strategy",
            "type": "link",
            "icon": ""
          }
        ]
      },
      {
        "state": "",
        "title": "Strategy 2",
        "icon": "",
        "type": "toggle",
        "pages": [
          {
            "state": "app.data.strategy-group({strategyNumber: 2})",
            "title": "Group",
            "type": "link",
            "icon": ""
          },
          {
            "state": "app.data.strategy-subgroup({strategyNumber: 2})",
            "title": "Subgroup",
            "type": "link",
            "icon": ""
          },
          {
            "state": "app.data.strategy({strategyNumber: 3})",
            "title": "Strategy",
            "type": "link",
            "icon": ""
          }
        ]
      },
      {
        "state": "",
        "title": "Strategy 3",
        "icon": "",
        "type": "toggle",
        "pages": [
          {
            "state": "app.data.strategy-group({strategyNumber: 3})",
            "title": "Group",
            "type": "link",
            "icon": ""
          },
          {
            "state": "app.data.strategy-subgroup({strategyNumber: 3})",
            "title": "Subgroup",
            "type": "link",
            "icon": ""
          },
          {
            "state": "app.data.strategy({strategyNumber: 3})",
            "title": "Strategy",
            "type": "link",
            "icon": ""
          }
        ]
      }
    ]
  },
  {
    "state": "app.actions",
    "title": "Actions",
    "type": "link",
    "icon": "assignment"
  },
  {
    "state": "",
    "title": "SETTINGS",
    "icon": "settings",
    "type": "toggle",
    "pages": [
      {
        "state": "app.settings.general.profile",
        "title": "General",
        "type": "link",
        "icon": ""
      },
      {
        "state": "app.settings.form-design",
        "title": "Form Design",
        "type": "link",
        "icon": ""
      },
      {
        "state": "app.settings.users-groups",
        "title": "Users & Groups",
        "type": "link",
        "icon": ""
      }
    ]
  },
  {
    "state": "",
    "title": "SYSTEM",
    "icon": "settings_system_daydream",
    "type": "toggle",
    "pages": [
      {
        "state": "app.system.notifications",
        "title": "Notifications",
        "type": "link",
        "icon": ""
      },
      {
        "state": "app.system.transactions",
        "title": "Audit transaction",
        "type": "link",
        "icon": ""
      },
      {
        "state": "app.system.instruments",
        "title": "Audit instrument",
        "type": "link",
        "icon": ""
      }
    ]
  }
]
